collection/__init__.py
collection/__main__.py
collection/unique_char_count.py
unique_character_counter-0.1.3.dist-info/LICENSE
unique_character_counter-0.1.3.dist-info/METADATA
unique_character_counter-0.1.3.dist-info/WHEEL
unique_character_counter-0.1.3.dist-info/entry_points.txt
unique_character_counter-0.1.3.dist-info/top_level.txt
unique_character_counter-0.1.3.dist-info/RECORD
