Metadata-Version: 2.1
Name: unique_character_counter
Version: 0.1.3
Summary: A project that calculates unique character counts with caching
Home-page: https://git.foxminded.ua/povh_andriy/task_3_collection_framework
Author: Andriy Povh
Author-email: andriypovh1233@gmail.com
License: MIT License
Classifier: Programming Language :: Python :: 3
Classifier: License :: OSI Approved :: MIT License
Classifier: Operating System :: OS Independent
Requires-Python: >=3.6
License-File: LICENSE
Requires-Dist: black==24.10.0
Requires-Dist: coverage==7.6.4
Requires-Dist: flake8==7.1.1
Requires-Dist: pytest==8.3.3
